setup.py
bin/restpi
restpi/__init__.py
restpi/channel.py
restpi/gpio.py
restpi.egg-info/PKG-INFO
restpi.egg-info/SOURCES.txt
restpi.egg-info/dependency_links.txt
restpi.egg-info/not-zip-safe
restpi.egg-info/pbr.json
restpi.egg-info/requires.txt
restpi.egg-info/top_level.txt