Metadata-Version: 1.0
Name: restpi
Version: 0.1
Summary: Nifty Library written in Python for controlling Raspberry Pi based devices remotely.
Home-page: http://github.com/andela-cnnadi/restpi
Author: Chidiebere Nnadi
Author-email: chidiebere.nnadi@gmail.com
License: MIT
Platform: UNKNOWN
